{
  "winning": [
    {
      "sequence": [
        "FOREHAND_RIGHT",
        "FOREHAND_RIGHT",
        "FOREHAND_RIGHT"
      ],
      "total": 27,
      "winnerRate": 0.8518518518518519,
      "uplift": 0.45313802548529236,
      "rankScore": 1.4934690097828358
    },
    {
      "sequence": [
        "T",
        "BACKHAND_LEFT"
      ],
      "total": 16,
      "winnerRate": 0.6875,
      "uplift": 0.2887861736334405,
      "rankScore": 0.8006852881548564
    },
    {
      "sequence": [
        "FOREHAND_RIGHT",
        "FOREHAND_RIGHT"
      ],
      "total": 110,
      "winnerRate": 0.5545454545454546,
      "uplift": 0.15583162817889507,
      "rankScore": 0.7324835086243605
    },
    {
      "sequence": [
        "BACKHAND_CENTER",
        "FOREHAND_RIGHT",
        "FOREHAND_RIGHT"
      ],
      "total": 19,
      "winnerRate": 0.631578947368421,
      "uplift": 0.23286512100186152,
      "rankScore": 0.6856571391661908
    },
    {
      "sequence": [
        "FOREHAND_CENTER",
        "BACKHAND_LEFT"
      ],
      "total": 47,
      "winnerRate": 0.5531914893617021,
      "uplift": 0.15447766299514265,
      "rankScore": 0.5947618036985232
    },
    {
      "sequence": [
        "FOREHAND_RIGHT",
        "FOREHAND_RIGHT",
        "FOREHAND_LEFT"
      ],
      "total": 33,
      "winnerRate": 0.5454545454545454,
      "uplift": 0.14674071908798592,
      "rankScore": 0.5130800338661714
    },
    {
      "sequence": [
        "BACKHAND_LEFT",
        "BACKHAND_CENTER"
      ],
      "total": 41,
      "winnerRate": 0.5365853658536586,
      "uplift": 0.13787153948709907,
      "rankScore": 0.5119958978328111
    },
    {
      "sequence": [
        "WIDE",
        "FOREHAND_CENTER"
      ],
      "total": 50,
      "winnerRate": 0.52,
      "uplift": 0.12128617363344052,
      "rankScore": 0.4744743014943719
    },
    {
      "sequence": [
        "T",
        "FOREHAND_LEFT"
      ],
      "total": 22,
      "winnerRate": 0.5454545454545454,
      "uplift": 0.14674071908798592,
      "rankScore": 0.45358179233729146
    },
    {
      "sequence": [
        "FOREHAND_LEFT",
        "BACKHAND_SLICE_LEFT"
      ],
      "total": 20,
      "winnerRate": 0.55,
      "uplift": 0.15128617363344055,
      "rankScore": 0.45321287289619067
    },
    {
      "sequence": [
        "FOREHAND_RIGHT",
        "FOREHAND_LEFT"
      ],
      "total": 89,
      "winnerRate": 0.4943820224719101,
      "uplift": 0.0956681961053506,
      "rankScore": 0.42941974446514336
    },
    {
      "sequence": [
        "FOREHAND_LEFT",
        "BACKHAND_LEFT",
        "BACKHAND_LEFT"
      ],
      "total": 23,
      "winnerRate": 0.5217391304347826,
      "uplift": 0.1230253040682231,
      "rankScore": 0.3857451293188384
    },
    {
      "sequence": [
        "FOREHAND_LEFT",
        "BACKHAND_CENTER"
      ],
      "total": 37,
      "winnerRate": 0.4864864864864865,
      "uplift": 0.08777266011992702,
      "rankScore": 0.3169398706674778
    },
    {
      "sequence": [
        "BACKHAND_LEFT",
        "BACKHAND_LEFT"
      ],
      "total": 119,
      "winnerRate": 0.46218487394957986,
      "uplift": 0.06347104758302036,
      "rankScore": 0.3033359746364124
    },
    {
      "sequence": [
        "FOREHAND_CENTER",
        "FOREHAND_CENTER"
      ],
      "total": 31,
      "winnerRate": 0.4838709677419355,
      "uplift": 0.085157141375376,
      "rankScore": 0.2924285338535738
    }
  ],
  "losing": [
    {
      "sequence": [
        "BACKHAND_SLICE_CENTER",
        "FOREHAND_RIGHT"
      ],
      "total": 23,
      "winnerRate": 0.13043478260869565,
      "uplift": -0.2682790437578638,
      "rankScore": -0.8411873899577853
    },
    {
      "sequence": [
        "T",
        "FOREHAND_CENTER",
        "FOREHAND_LEFT"
      ],
      "total": 15,
      "winnerRate": 0.13333333333333333,
      "uplift": -0.2653804930332262,
      "rankScore": -0.7186636975272318
    },
    {
      "sequence": [
        "WIDE",
        "BACKHAND_CENTER"
      ],
      "total": 43,
      "winnerRate": 0.23255813953488372,
      "uplift": -0.16615568683167578,
      "rankScore": -0.6249447885344422
    },
    {
      "sequence": [
        "BACKHAND_LEFT",
        "BACKHAND_SLICE_CENTER"
      ],
      "total": 20,
      "winnerRate": 0.2,
      "uplift": -0.1987138263665595,
      "rankScore": -0.5952934228477063
    },
    {
      "sequence": [
        "T",
        "FOREHAND_CENTER"
      ],
      "total": 38,
      "winnerRate": 0.23684210526315788,
      "uplift": -0.16187172110340162,
      "rankScore": -0.5888223323368232
    },
    {
      "sequence": [
        "FOREHAND_LEFT",
        "FOREHAND_LEFT"
      ],
      "total": 18,
      "winnerRate": 0.2222222222222222,
      "uplift": -0.1764916041443373,
      "rankScore": -0.5101263481245821
    },
    {
      "sequence": [
        "FOREHAND_LEFT",
        "BACKHAND_RIGHT"
      ],
      "total": 31,
      "winnerRate": 0.25806451612903225,
      "uplift": -0.14064931023752725,
      "rankScore": -0.4829879316753303
    },
    {
      "sequence": [
        "FOREHAND_RIGHT",
        "BACKHAND_CENTER"
      ],
      "total": 31,
      "winnerRate": 0.25806451612903225,
      "uplift": -0.14064931023752725,
      "rankScore": -0.4829879316753303
    },
    {
      "sequence": [
        "BACKHAND_CENTER",
        "FOREHAND_LEFT",
        "BACKHAND_LEFT"
      ],
      "total": 16,
      "winnerRate": 0.25,
      "uplift": -0.1487138263665595,
      "rankScore": -0.4123222778250479
    },
    {
      "sequence": [
        "BACKHAND_LEFT",
        "BACKHAND_LEFT",
        "BACKHAND_LEFT",
        "BACKHAND_LEFT"
      ],
      "total": 16,
      "winnerRate": 0.3125,
      "uplift": -0.0862138263665595,
      "rankScore": -0.23903548268506156
    },
    {
      "sequence": [
        "FOREHAND_CENTER",
        "FOREHAND_LEFT"
      ],
      "total": 53,
      "winnerRate": 0.33962264150943394,
      "uplift": -0.059091184857125556,
      "rankScore": -0.23460925340045918
    },
    {
      "sequence": [
        "WIDE",
        "BACKHAND_CENTER",
        "FOREHAND_RIGHT"
      ],
      "total": 15,
      "winnerRate": 0.3333333333333333,
      "uplift": -0.06538049303322618,
      "rankScore": -0.17705365730678982
    },
    {
      "sequence": [
        "T",
        "BACKHAND_SLICE_CENTER"
      ],
      "total": 20,
      "winnerRate": 0.35,
      "uplift": -0.04871382636655952,
      "rankScore": -0.1459335818146077
    },
    {
      "sequence": [
        "BACKHAND_CENTER",
        "FOREHAND_LEFT"
      ],
      "total": 54,
      "winnerRate": 0.37037037037037035,
      "uplift": -0.02834345599618915,
      "rankScore": -0.11306159379329504
    },
    {
      "sequence": [
        "BACKHAND_RIGHT",
        "FOREHAND_LEFT"
      ],
      "total": 19,
      "winnerRate": 0.3684210526315789,
      "uplift": -0.03029277373498057,
      "rankScore": -0.08919522377234615
    }
  ]
}