[
  {
    "shotType": "SERVE",
    "total": 566,
    "winnerRate": 0.4717314487632509,
    "adjustedEffectiveness": 0.07648496989001147,
    "confidence": "high"
  },
  {
    "shotType": "FOREHAND",
    "total": 506,
    "winnerRate": 0.4031620553359684,
    "adjustedEffectiveness": 0.007915576462728946,
    "confidence": "high"
  },
  {
    "shotType": "BACKHAND",
    "total": 339,
    "winnerRate": 0.415929203539823,
    "adjustedEffectiveness": 0.020682724666583552,
    "confidence": "high"
  },
  {
    "shotType": "BACKHAND_SLICE",
    "total": 189,
    "winnerRate": 0.4973544973544973,
    "adjustedEffectiveness": 0.10210801848125789,
    "confidence": "high"
  },
  {
    "shotType": "BACKHAND_VOLLEY",
    "total": 47,
    "winnerRate": 0.5106382978723404,
    "adjustedEffectiveness": 0.11539181899910095,
    "confidence": "high"
  },
  {
    "shotType": "FOREHAND_SLICE",
    "total": 42,
    "winnerRate": 0.2619047619047619,
    "adjustedEffectiveness": -0.13334171696847752,
    "confidence": "high"
  },
  {
    "shotType": "FOREHAND_VOLLEY",
    "total": 30,
    "winnerRate": 0.6333333333333333,
    "adjustedEffectiveness": 0.23808685446009387,
    "confidence": "high"
  },
  {
    "shotType": "SMASH",
    "total": 24,
    "winnerRate": 0.5,
    "adjustedEffectiveness": 0.10475352112676056,
    "confidence": "low"
  }
]