[{"serveDir":"WIDE","responseType":"FOREHAND","total":1099,"winners":16,"errors":340,"winnerRate":0.015,"errorRate":0.309,"winnerCI":{"lower":0.008981,"upper":0.023518,"center":0.01625},"errorCI":{"lower":0.282747,"upper":0.337325,"center":0.310036},"confidence":"high"},{"serveDir":"WIDE","responseType":"BACKHAND","total":1029,"winners":16,"errors":188,"winnerRate":0.016,"errorRate":0.183,"winnerCI":{"lower":0.009593,"upper":0.025109,"center":0.017351},"errorCI":{"lower":0.160285,"upper":0.207478,"center":0.183882},"confidence":"high"},{"serveDir":"T","responseType":"FOREHAND","total":931,"winners":6,"errors":206,"winnerRate":0.006,"errorRate":0.221,"winnerCI":{"lower":0.002957,"upper":0.013989,"center":0.008473},"errorCI":{"lower":0.195779,"upper":0.249047,"center":0.222413},"confidence":"high"},{"serveDir":"T","responseType":"BACKHAND","total":815,"winners":2,"errors":142,"winnerRate":0.002,"errorRate":0.174,"winnerCI":{"lower":0.000673,"upper":0.008903,"center":0.004788},"errorCI":{"lower":0.149736,"upper":0.201787,"center":0.175761},"confidence":"high"},{"serveDir":"BODY","responseType":"BACKHAND","total":560,"winners":2,"errors":93,"winnerRate":0.004,"errorRate":0.166,"winnerCI":{"lower":0.00098,"upper":0.012928,"center":0.006954},"errorCI":{"lower":0.137545,"upper":0.199148,"center":0.168347},"confidence":"high"},{"serveDir":"BODY","responseType":"FOREHAND","total":362,"winners":7,"errors":64,"winnerRate":0.019,"errorRate":0.177,"winnerCI":{"lower":0.009398,"upper":0.039371,"center":0.024384},"errorCI":{"lower":0.140949,"upper":0.21943,"center":0.180189},"confidence":"high"},{"serveDir":"T","responseType":"BACKHAND_SLICE","total":301,"winners":0,"errors":93,"winnerRate":0,"errorRate":0.309,"winnerCI":{"lower":0,"upper":0.012602,"center":0.006301},"errorCI":{"lower":0.25945,"upper":0.363304,"center":0.311377},"confidence":"high"},{"serveDir":"WIDE","responseType":"BACKHAND_SLICE","total":277,"winners":1,"errors":65,"winnerRate":0.004,"errorRate":0.235,"winnerCI":{"lower":0.000638,"upper":0.020163,"center":0.0104},"errorCI":{"lower":0.188589,"upper":0.287984,"center":0.238287},"confidence":"high"},{"serveDir":"WIDE","responseType":"FOREHAND_SLICE","total":150,"winners":1,"errors":39,"winnerRate":0.007,"errorRate":0.26,"winnerCI":{"lower":0.001178,"upper":0.036794,"center":0.018986},"errorCI":{"lower":0.19642,"upper":0.335566,"center":0.265993},"confidence":"high"},{"serveDir":"T","responseType":"FOREHAND_SLICE","total":102,"winners":0,"errors":26,"winnerRate":0,"errorRate":0.255,"winnerCI":{"lower":0,"upper":0.036296,"center":0.018148},"errorCI":{"lower":0.180295,"upper":0.347301,"center":0.263798},"confidence":"high"},{"serveDir":"BODY","responseType":"BACKHAND_SLICE","total":79,"winners":0,"errors":14,"winnerRate":0,"errorRate":0.177,"winnerCI":{"lower":0,"upper":0.046373,"center":0.023186},"errorCI":{"lower":0.108603,"upper":0.275764,"center":0.192184},"confidence":"high"},{"serveDir":"BODY","responseType":"FOREHAND_SLICE","total":50,"winners":0,"errors":6,"winnerRate":0,"errorRate":0.12,"winnerCI":{"lower":0,"upper":0.07135,"center":0.035675},"errorCI":{"lower":0.056175,"upper":0.238051,"center":0.147113},"confidence":"high"},{"serveDir":"T","responseType":"BACKHAND_LOB","total":8,"winners":0,"errors":2,"winnerRate":0,"errorRate":0.25,"winnerCI":{"lower":0,"upper":0.324416,"center":0.162208},"errorCI":{"lower":0.071478,"upper":0.59073,"center":0.331104},"confidence":"insufficient"},{"serveDir":"WIDE","responseType":"BACKHAND_LOB","total":6,"winners":0,"errors":0,"winnerRate":0,"errorRate":0,"winnerCI":{"lower":0,"upper":0.390343,"center":0.195172},"errorCI":{"lower":0,"upper":0.390343,"center":0.195172},"confidence":"insufficient"}]