{
  "winning": [
    {
      "sequence": [
        "BACKHAND_LEFT",
        "BACKHAND_LEFT"
      ],
      "total": 19,
      "winnerRate": 0.631578947368421,
      "uplift": 0.27602339181286545,
      "rankScore": 0.8127340340155319
    },
    {
      "sequence": [
        "FOREHAND_LEFT",
        "BACKHAND_CENTER"
      ],
      "total": 21,
      "winnerRate": 0.38095238095238093,
      "uplift": 0.025396825396825362,
      "rankScore": 0.0773212047675789
    },
    {
      "sequence": [
        "FOREHAND_RIGHT",
        "FOREHAND_RIGHT"
      ],
      "total": 32,
      "winnerRate": 0.375,
      "uplift": 0.01944444444444443,
      "rankScore": 0.06738930922110575
    }
  ],
  "losing": [
    {
      "sequence": [
        "FOREHAND_LEFT",
        "BACKHAND_LEFT"
      ],
      "total": 23,
      "winnerRate": 0.30434782608695654,
      "uplift": -0.05120772946859903,
      "rankScore": -0.16056153955965694
    },
    {
      "sequence": [
        "FOREHAND_CENTER",
        "FOREHAND_RIGHT"
      ],
      "total": 19,
      "winnerRate": 0.3157894736842105,
      "uplift": -0.03976608187134506,
      "rankScore": -0.11708880151071234
    },
    {
      "sequence": [
        "FOREHAND_CENTER",
        "FOREHAND_LEFT"
      ],
      "total": 19,
      "winnerRate": 0.3157894736842105,
      "uplift": -0.03976608187134506,
      "rankScore": -0.11708880151071234
    },
    {
      "sequence": [
        "FOREHAND_CENTER",
        "FOREHAND_CENTER"
      ],
      "total": 18,
      "winnerRate": 0.3333333333333333,
      "uplift": -0.022222222222222254,
      "rankScore": -0.06423048350880375
    },
    {
      "sequence": [
        "FOREHAND_RIGHT",
        "FOREHAND_CENTER"
      ],
      "total": 31,
      "winnerRate": 0.3548387096774194,
      "uplift": -0.0007168458781361964,
      "rankScore": -0.0024616395731076168
    }
  ]
}