[
  {
    "shotType": "SERVE",
    "total": 2954,
    "winnerRate": 0.519634394041977,
    "adjustedEffectiveness": 0.13584053067530466,
    "confidence": "high"
  },
  {
    "shotType": "FOREHAND",
    "total": 1774,
    "winnerRate": 0.3765501691093574,
    "adjustedEffectiveness": -0.007243694257314914,
    "confidence": "high"
  },
  {
    "shotType": "BACKHAND",
    "total": 1312,
    "winnerRate": 0.3597560975609756,
    "adjustedEffectiveness": -0.02403776580569672,
    "confidence": "high"
  },
  {
    "shotType": "BACKHAND_SLICE",
    "total": 382,
    "winnerRate": 0.23821989528795812,
    "adjustedEffectiveness": -0.1455739680787142,
    "confidence": "high"
  },
  {
    "shotType": "FOREHAND_SLICE",
    "total": 278,
    "winnerRate": 0.2589928057553957,
    "adjustedEffectiveness": -0.12480105761127663,
    "confidence": "high"
  },
  {
    "shotType": "BACKHAND_VOLLEY",
    "total": 76,
    "winnerRate": 0.34210526315789475,
    "adjustedEffectiveness": -0.04168860020877757,
    "confidence": "high"
  },
  {
    "shotType": "FOREHAND_VOLLEY",
    "total": 65,
    "winnerRate": 0.5230769230769231,
    "adjustedEffectiveness": 0.1392830597102508,
    "confidence": "high"
  },
  {
    "shotType": "SMASH",
    "total": 31,
    "winnerRate": 0.7096774193548387,
    "adjustedEffectiveness": 0.32588355598816643,
    "confidence": "high"
  },
  {
    "shotType": "FOREHAND_DROP",
    "total": 26,
    "winnerRate": 0.5,
    "adjustedEffectiveness": 0.11620613663332768,
    "confidence": "low"
  },
  {
    "shotType": "BACKHAND_LOB",
    "total": 18,
    "winnerRate": 0.2777777777777778,
    "adjustedEffectiveness": -0.10601608558889453,
    "confidence": "low"
  },
  {
    "shotType": "FOREHAND_LOB",
    "total": 16,
    "winnerRate": 0.1875,
    "adjustedEffectiveness": -0.19629386336667232,
    "confidence": "low"
  }
]