{
  "winning": [
    {
      "sequence": [
        "BACKHAND_RIGHT",
        "FOREHAND_RIGHT"
      ],
      "total": 17,
      "winnerRate": 0.5294117647058824,
      "uplift": 0.14504694385897682,
      "rankScore": 0.41094893685582595
    },
    {
      "sequence": [
        "FOREHAND_CENTER",
        "BACKHAND_LEFT"
      ],
      "total": 17,
      "winnerRate": 0.5294117647058824,
      "uplift": 0.14504694385897682,
      "rankScore": 0.41094893685582595
    },
    {
      "sequence": [
        "BACKHAND_CENTER",
        "BACKHAND_CENTER"
      ],
      "total": 36,
      "winnerRate": 0.4722222222222222,
      "uplift": 0.08785740137531667,
      "rankScore": 0.31483866171198716
    },
    {
      "sequence": [
        "WIDE",
        "FOREHAND_CENTER"
      ],
      "total": 41,
      "winnerRate": 0.4634146341463415,
      "uplift": 0.07904981329943594,
      "rankScore": 0.29355717854697605
    },
    {
      "sequence": [
        "FOREHAND_RIGHT",
        "FOREHAND_LEFT",
        "BACKHAND_LEFT"
      ],
      "total": 17,
      "winnerRate": 0.47058823529411764,
      "uplift": 0.0862234144472121,
      "rankScore": 0.24428932838193085
    },
    {
      "sequence": [
        "FOREHAND_RIGHT",
        "FOREHAND_LEFT"
      ],
      "total": 41,
      "winnerRate": 0.43902439024390244,
      "uplift": 0.0546595693969969,
      "rankScore": 0.2029822500907733
    },
    {
      "sequence": [
        "FOREHAND_LEFT",
        "BACKHAND_LEFT",
        "BACKHAND_LEFT"
      ],
      "total": 20,
      "winnerRate": 0.45,
      "uplift": 0.06563517915309447,
      "rankScore": 0.1966254244694232
    },
    {
      "sequence": [
        "BACKHAND_LEFT",
        "BACKHAND_CENTER"
      ],
      "total": 37,
      "winnerRate": 0.43243243243243246,
      "uplift": 0.048067611585526915,
      "rankScore": 0.1735681996922042
    },
    {
      "sequence": [
        "BACKHAND_CENTER",
        "FOREHAND_CENTER"
      ],
      "total": 49,
      "winnerRate": 0.42857142857142855,
      "uplift": 0.044206607724523006,
      "rankScore": 0.17204417325291266
    },
    {
      "sequence": [
        "FOREHAND_CENTER",
        "BACKHAND_CENTER"
      ],
      "total": 50,
      "winnerRate": 0.42,
      "uplift": 0.03563517915309444,
      "rankScore": 0.13940564064945893
    },
    {
      "sequence": [
        "T",
        "BACKHAND_CENTER"
      ],
      "total": 58,
      "winnerRate": 0.41379310344827586,
      "uplift": 0.029428282601370315,
      "rankScore": 0.11949186440111889
    },
    {
      "sequence": [
        "FOREHAND_CENTER",
        "FOREHAND_RIGHT"
      ],
      "total": 19,
      "winnerRate": 0.42105263157894735,
      "uplift": 0.0366878107320418,
      "rankScore": 0.10802501997970473
    },
    {
      "sequence": [
        "BACKHAND_SLICE_CENTER",
        "FOREHAND_LEFT"
      ],
      "total": 17,
      "winnerRate": 0.4117647058823529,
      "uplift": 0.02739988503544738,
      "rankScore": 0.07762971990803574
    },
    {
      "sequence": [
        "FOREHAND_LEFT",
        "BACKHAND_CENTER"
      ],
      "total": 53,
      "winnerRate": 0.39622641509433965,
      "uplift": 0.011861594247434104,
      "rankScore": 0.04709399172242399
    },
    {
      "sequence": [
        "BACKHAND_CENTER",
        "FOREHAND_CENTER",
        "BACKHAND_CENTER"
      ],
      "total": 20,
      "winnerRate": 0.4,
      "uplift": 0.01563517915309448,
      "rankScore": 0.04683881079172369
    }
  ],
  "losing": [
    {
      "sequence": [
        "T",
        "FOREHAND_CENTER_FORCED_ERROR"
      ],
      "total": 16,
      "winnerRate": 0.0625,
      "uplift": -0.32186482084690554,
      "rankScore": -0.892398772365858
    },
    {
      "sequence": [
        "BACKHAND_LEFT",
        "BACKHAND_LEFT",
        "BACKHAND_LEFT"
      ],
      "total": 26,
      "winnerRate": 0.23076923076923078,
      "uplift": -0.15359559007767476,
      "rankScore": -0.5004292602874388
    },
    {
      "sequence": [
        "WIDE",
        "BACKHAND_CENTER"
      ],
      "total": 47,
      "winnerRate": 0.2553191489361702,
      "uplift": -0.12904567191073535,
      "rankScore": -0.49684488421818074
    },
    {
      "sequence": [
        "FOREHAND_RIGHT",
        "FOREHAND_RIGHT"
      ],
      "total": 47,
      "winnerRate": 0.2765957446808511,
      "uplift": -0.10776907616605447,
      "rankScore": -0.41492685013924324
    },
    {
      "sequence": [
        "WIDE",
        "BACKHAND_LEFT"
      ],
      "total": 23,
      "winnerRate": 0.2608695652173913,
      "uplift": -0.12349525562951424,
      "rankScore": -0.3872186597210337
    },
    {
      "sequence": [
        "FOREHAND_RIGHT",
        "FOREHAND_CENTER"
      ],
      "total": 38,
      "winnerRate": 0.2894736842105263,
      "uplift": -0.09489113663637921,
      "rankScore": -0.3451746853091984
    },
    {
      "sequence": [
        "BACKHAND_LEFT",
        "BACKHAND_LEFT"
      ],
      "total": 78,
      "winnerRate": 0.32051282051282054,
      "uplift": -0.063852000334085,
      "rankScore": -0.27818457345729486
    },
    {
      "sequence": [
        "BACKHAND_LEFT",
        "FOREHAND_LEFT"
      ],
      "total": 26,
      "winnerRate": 0.3076923076923077,
      "uplift": -0.07667251315459783,
      "rankScore": -0.24980644967040175
    },
    {
      "sequence": [
        "BACKHAND_CENTER",
        "FOREHAND_RIGHT"
      ],
      "total": 55,
      "winnerRate": 0.32727272727272727,
      "uplift": -0.05709209357417827,
      "rankScore": -0.22878704119420212
    },
    {
      "sequence": [
        "BACKHAND_CENTER",
        "FOREHAND_LEFT"
      ],
      "total": 51,
      "winnerRate": 0.3333333333333333,
      "uplift": -0.05103148751357223,
      "rankScore": -0.20064691068191465
    },
    {
      "sequence": [
        "FOREHAND_RIGHT",
        "FOREHAND_RIGHT",
        "FOREHAND_LEFT"
      ],
      "total": 16,
      "winnerRate": 0.3125,
      "uplift": -0.07186482084690554,
      "rankScore": -0.19925159180591262
    },
    {
      "sequence": [
        "T",
        "FOREHAND_CENTER"
      ],
      "total": 41,
      "winnerRate": 0.34146341463414637,
      "uplift": -0.042901406212759174,
      "rankScore": -0.15931746373403713
    },
    {
      "sequence": [
        "FOREHAND_LEFT",
        "BACKHAND_SLICE_CENTER"
      ],
      "total": 15,
      "winnerRate": 0.3333333333333333,
      "uplift": -0.05103148751357223,
      "rankScore": -0.1381958300236742
    },
    {
      "sequence": [
        "FOREHAND_CENTER",
        "FOREHAND_LEFT"
      ],
      "total": 31,
      "winnerRate": 0.3548387096774194,
      "uplift": -0.02952611116948617,
      "rankScore": -0.10139228795422146
    },
    {
      "sequence": [
        "BACKHAND_CENTER",
        "BACKHAND_LEFT"
      ],
      "total": 19,
      "winnerRate": 0.3684210526315789,
      "uplift": -0.015943768215326615,
      "rankScore": -0.04694545260800263
    }
  ]
}