[{"direction":"T","total":8060,"winners":0,"errors":0,"inPlay":8060,"winnerRate":0,"errorRate":0,"winnerCI":{"lower":0,"upper":0.000476,"center":0.000238},"errorCI":{"lower":0,"upper":0.000476,"center":0.000238},"confidence":"high"},{"direction":"BODY","total":2245,"winners":0,"errors":0,"inPlay":2245,"winnerRate":0,"errorRate":0,"winnerCI":{"lower":0,"upper":0.001708,"center":0.000854},"errorCI":{"lower":0,"upper":0.001708,"center":0.000854},"confidence":"high"},{"direction":"WIDE","total":7541,"winners":0,"errors":0,"inPlay":7541,"winnerRate":0,"errorRate":0,"winnerCI":{"lower":0,"upper":0.000509,"center":0.000255},"errorCI":{"lower":0,"upper":0.000509,"center":0.000255},"confidence":"high"}]