[
  {
    "shotType": "FOREHAND",
    "total": 118,
    "winnerRate": 0.4491525423728814,
    "adjustedEffectiveness": 0.09359698681732581,
    "confidence": "high"
  },
  {
    "shotType": "BACKHAND",
    "total": 88,
    "winnerRate": 0.4659090909090909,
    "adjustedEffectiveness": 0.11035353535353531,
    "confidence": "high"
  },
  {
    "shotType": "SERVE",
    "total": 68,
    "winnerRate": 0.47058823529411764,
    "adjustedEffectiveness": 0.11503267973856207,
    "confidence": "high"
  }
]