[
  {
    "shotType": "SERVE",
    "total": 1145,
    "winnerRate": 0.4943231441048035,
    "adjustedEffectiveness": 0.111353711790393,
    "confidence": "high"
  },
  {
    "shotType": "FOREHAND",
    "total": 1096,
    "winnerRate": 0.3768248175182482,
    "adjustedEffectiveness": -0.0061446147961622954,
    "confidence": "high"
  },
  {
    "shotType": "BACKHAND",
    "total": 796,
    "winnerRate": 0.3316582914572864,
    "adjustedEffectiveness": -0.05131114085712407,
    "confidence": "high"
  },
  {
    "shotType": "BACKHAND_SLICE",
    "total": 203,
    "winnerRate": 0.19704433497536947,
    "adjustedEffectiveness": -0.18592509733904103,
    "confidence": "high"
  },
  {
    "shotType": "FOREHAND_SLICE",
    "total": 76,
    "winnerRate": 0.21052631578947367,
    "adjustedEffectiveness": -0.17244311652493682,
    "confidence": "high"
  },
  {
    "shotType": "FOREHAND_VOLLEY",
    "total": 23,
    "winnerRate": 0.4782608695652174,
    "adjustedEffectiveness": 0.09529143725080691,
    "confidence": "low"
  },
  {
    "shotType": "SMASH",
    "total": 21,
    "winnerRate": 0.6666666666666666,
    "adjustedEffectiveness": 0.28369723435225613,
    "confidence": "low"
  },
  {
    "shotType": "BACKHAND_VOLLEY",
    "total": 18,
    "winnerRate": 0.2777777777777778,
    "adjustedEffectiveness": -0.1051916545366327,
    "confidence": "low"
  },
  {
    "shotType": "BACKHAND_LOB",
    "total": 15,
    "winnerRate": 0.2,
    "adjustedEffectiveness": -0.18296943231441049,
    "confidence": "low"
  }
]