[
  {
    "serveDir": "T",
    "responseType": "FOREHAND",
    "total": 49,
    "winnerRate": 0.5102040816326531,
    "adjustedEffectiveness": 0.06664287336556246
  },
  {
    "serveDir": "T",
    "responseType": "BACKHAND",
    "total": 47,
    "winnerRate": 0.40425531914893614,
    "adjustedEffectiveness": -0.03930588911815447
  },
  {
    "serveDir": "BODY",
    "responseType": "BACKHAND",
    "total": 24,
    "winnerRate": 0.4583333333333333,
    "adjustedEffectiveness": 0.014772125066242703
  },
  {
    "serveDir": "WIDE",
    "responseType": "FOREHAND",
    "total": 64,
    "winnerRate": 0.46875,
    "adjustedEffectiveness": 0.025188791732909388
  },
  {
    "serveDir": "WIDE",
    "responseType": "BACKHAND",
    "total": 85,
    "winnerRate": 0.3764705882352941,
    "adjustedEffectiveness": -0.0670906200317965
  }
]