{
  "wins": [
    {
      "shotType": "BACKHAND",
      "total": 111,
      "winnerRate": 0.3783783783783784,
      "adjustedEffectiveness": -0.020035893177617614
    },
    {
      "shotType": "BACKHAND_SLICE",
      "total": 41,
      "winnerRate": 0.3170731707317073,
      "adjustedEffectiveness": -0.08134110082428869
    },
    {
      "shotType": "FOREHAND",
      "total": 155,
      "winnerRate": 0.3935483870967742,
      "adjustedEffectiveness": -0.004865884459221814
    },
    {
      "shotType": "SERVE",
      "total": 161,
      "winnerRate": 0.5031055900621118,
      "adjustedEffectiveness": 0.10469131850611574
    }
  ],
  "losses": [
    {
      "shotType": "BACKHAND",
      "total": 182,
      "winnerRate": 0.33516483516483514,
      "adjustedEffectiveness": -0.06324943639116087
    },
    {
      "shotType": "BACKHAND_LOB",
      "total": 18,
      "winnerRate": 0.1111111111111111,
      "adjustedEffectiveness": -0.2873031604448849
    },
    {
      "shotType": "BACKHAND_SLICE",
      "total": 93,
      "winnerRate": 0.34408602150537637,
      "adjustedEffectiveness": -0.05432825005061964
    },
    {
      "shotType": "FOREHAND",
      "total": 319,
      "winnerRate": 0.3448275862068966,
      "adjustedEffectiveness": -0.05358668534909944
    },
    {
      "shotType": "FOREHAND_SLICE",
      "total": 39,
      "winnerRate": 0.23076923076923078,
      "adjustedEffectiveness": -0.16764504078676523
    },
    {
      "shotType": "SERVE",
      "total": 342,
      "winnerRate": 0.4444444444444444,
      "adjustedEffectiveness": 0.046030172888448406
    }
  ]
}