[{"shotType":"FOREHAND","total":1284,"winners":75,"unforcedErrors":109,"forcedErrors":95,"effectiveness":-0.1,"winnerRate":0.058,"errorRate":0.159,"winnerCI":{"lower":0.046852,"upper":0.072605,"center":0.059728},"errorCI":{"lower":0.139904,"upper":0.179888,"center":0.159896},"confidence":"high"},{"shotType":"SERVE","total":1123,"winners":0,"unforcedErrors":0,"forcedErrors":0,"effectiveness":0,"winnerRate":0,"errorRate":0,"winnerCI":{"lower":0,"upper":0.003409,"center":0.001705},"errorCI":{"lower":0,"upper":0.003409,"center":0.001705},"confidence":"high"},{"shotType":"BACKHAND","total":1040,"winners":36,"unforcedErrors":66,"forcedErrors":66,"effectiveness":-0.092,"winnerRate":0.035,"errorRate":0.127,"winnerCI":{"lower":0.025107,"upper":0.047549,"center":0.036328},"errorCI":{"lower":0.108055,"upper":0.148537,"center":0.128296},"confidence":"high"},{"shotType":"BACKHAND_SLICE","total":281,"winners":0,"unforcedErrors":14,"forcedErrors":36,"effectiveness":-0.178,"winnerRate":0,"errorRate":0.178,"winnerCI":{"lower":0,"upper":0.013487,"center":0.006743},"errorCI":{"lower":0.137652,"upper":0.226907,"center":0.18228},"confidence":"high"},{"shotType":"FOREHAND_SLICE","total":163,"winners":0,"unforcedErrors":5,"forcedErrors":34,"effectiveness":-0.239,"winnerRate":0,"errorRate":0.239,"winnerCI":{"lower":0,"upper":0.023025,"center":0.011513},"errorCI":{"lower":0.180252,"upper":0.310283,"center":0.245267},"confidence":"high"},{"shotType":"BACKHAND_LOB","total":42,"winners":2,"unforcedErrors":0,"forcedErrors":8,"effectiveness":-0.143,"winnerRate":0.048,"errorRate":0.19,"winnerCI":{"lower":0.013157,"upper":0.157901,"center":0.085529},"errorCI":{"lower":0.099819,"upper":0.333011,"center":0.216415},"confidence":"high"},{"shotType":"SMASH","total":36,"winners":17,"unforcedErrors":4,"forcedErrors":0,"effectiveness":0.361,"winnerRate":0.472,"errorRate":0.111,"winnerCI":{"lower":0.319858,"upper":0.629943,"center":0.474901},"errorCI":{"lower":0.044066,"upper":0.253151,"center":0.148608},"confidence":"high"},{"shotType":"BACKHAND_DROP","total":34,"winners":3,"unforcedErrors":1,"forcedErrors":3,"effectiveness":-0.029,"winnerRate":0.088,"errorRate":0.118,"winnerCI":{"lower":0.030465,"upper":0.229608,"center":0.130037},"errorCI":{"lower":0.046714,"upper":0.266212,"center":0.156463},"confidence":"high"},{"shotType":"FOREHAND_VOLLEY","total":27,"winners":9,"unforcedErrors":4,"forcedErrors":5,"effectiveness":0,"winnerRate":0.333,"errorRate":0.333,"winnerCI":{"lower":0.186431,"upper":0.521756,"center":0.354093},"errorCI":{"lower":0.186431,"upper":0.521756,"center":0.354093},"confidence":"low"},{"shotType":"BACKHAND_VOLLEY","total":26,"winners":12,"unforcedErrors":1,"forcedErrors":5,"effectiveness":0.231,"winnerRate":0.462,"errorRate":0.231,"winnerCI":{"lower":0.287556,"upper":0.645424,"center":0.46649},"errorCI":{"lower":0.110337,"upper":0.420519,"center":0.265428},"confidence":"low"},{"shotType":"FOREHAND_LOB","total":25,"winners":1,"unforcedErrors":0,"forcedErrors":4,"effectiveness":-0.12,"winnerRate":0.04,"errorRate":0.16,"winnerCI":{"lower":0.007096,"upper":0.195445,"center":0.10127},"errorCI":{"lower":0.064033,"upper":0.34654,"center":0.205287},"confidence":"low"},{"shotType":"FOREHAND_SWINGING_VOLLEY","total":12,"winners":5,"unforcedErrors":1,"forcedErrors":0,"effectiveness":0.333,"winnerRate":0.417,"errorRate":0.083,"winnerCI":{"lower":0.193257,"upper":0.680493,"center":0.436875},"errorCI":{"lower":0.014865,"upper":0.353886,"center":0.184375},"confidence":"low"}]