{
  "wins": [
    {
      "shotType": "BACKHAND",
      "total": 862,
      "winnerRate": 0.302784222737819,
      "adjustedEffectiveness": -0.08362726051576952
    },
    {
      "shotType": "BACKHAND_DROP",
      "total": 25,
      "winnerRate": 0.4,
      "adjustedEffectiveness": 0.013588516746411483
    },
    {
      "shotType": "BACKHAND_LOB",
      "total": 55,
      "winnerRate": 0.2,
      "adjustedEffectiveness": -0.18641148325358853
    },
    {
      "shotType": "BACKHAND_SLICE",
      "total": 202,
      "winnerRate": 0.2623762376237624,
      "adjustedEffectiveness": -0.12403524562982615
    },
    {
      "shotType": "BACKHAND_VOLLEY",
      "total": 52,
      "winnerRate": 0.38461538461538464,
      "adjustedEffectiveness": -0.0017960986382039024
    },
    {
      "shotType": "FOREHAND",
      "total": 1267,
      "winnerRate": 0.3764798737174428,
      "adjustedEffectiveness": -0.009931609536145747
    },
    {
      "shotType": "FOREHAND_DROP",
      "total": 38,
      "winnerRate": 0.5,
      "adjustedEffectiveness": 0.11358851674641146
    },
    {
      "shotType": "FOREHAND_LOB",
      "total": 33,
      "winnerRate": 0.24242424242424243,
      "adjustedEffectiveness": -0.1439872408293461
    },
    {
      "shotType": "FOREHAND_SLICE",
      "total": 127,
      "winnerRate": 0.16535433070866143,
      "adjustedEffectiveness": -0.2210571525449271
    },
    {
      "shotType": "FOREHAND_VOLLEY",
      "total": 55,
      "winnerRate": 0.5636363636363636,
      "adjustedEffectiveness": 0.17722488038277506
    },
    {
      "shotType": "SERVE",
      "total": 1359,
      "winnerRate": 0.48344370860927155,
      "adjustedEffectiveness": 0.09703222535568301
    },
    {
      "shotType": "SMASH",
      "total": 46,
      "winnerRate": 0.6521739130434783,
      "adjustedEffectiveness": 0.26576242978988973
    }
  ],
  "losses": [
    {
      "shotType": "BACKHAND",
      "total": 799,
      "winnerRate": 0.31789737171464333,
      "adjustedEffectiveness": -0.06851411153894521
    },
    {
      "shotType": "BACKHAND_DROP",
      "total": 18,
      "winnerRate": 0.3888888888888889,
      "adjustedEffectiveness": 0.002477405635300356
    },
    {
      "shotType": "BACKHAND_LOB",
      "total": 53,
      "winnerRate": 0.07547169811320754,
      "adjustedEffectiveness": -0.310939785140381
    },
    {
      "shotType": "BACKHAND_SLICE",
      "total": 196,
      "winnerRate": 0.23469387755102042,
      "adjustedEffectiveness": -0.15171760570256812
    },
    {
      "shotType": "BACKHAND_VOLLEY",
      "total": 35,
      "winnerRate": 0.34285714285714286,
      "adjustedEffectiveness": -0.04355434039644568
    },
    {
      "shotType": "FOREHAND",
      "total": 1159,
      "winnerRate": 0.3796376186367558,
      "adjustedEffectiveness": -0.006773864616832714
    },
    {
      "shotType": "FOREHAND_DROP",
      "total": 28,
      "winnerRate": 0.5,
      "adjustedEffectiveness": 0.11358851674641146
    },
    {
      "shotType": "FOREHAND_LOB",
      "total": 28,
      "winnerRate": 0.07142857142857142,
      "adjustedEffectiveness": -0.31498291182501714
    },
    {
      "shotType": "FOREHAND_SLICE",
      "total": 99,
      "winnerRate": 0.18181818181818182,
      "adjustedEffectiveness": -0.20459330143540672
    },
    {
      "shotType": "FOREHAND_VOLLEY",
      "total": 35,
      "winnerRate": 0.5714285714285714,
      "adjustedEffectiveness": 0.18501708817498286
    },
    {
      "shotType": "SERVE",
      "total": 1253,
      "winnerRate": 0.4389465283320032,
      "adjustedEffectiveness": 0.052535045078414666
    },
    {
      "shotType": "SMASH",
      "total": 39,
      "winnerRate": 0.717948717948718,
      "adjustedEffectiveness": 0.3315372346951294
    }
  ]
}