{
  "wins": [
    {
      "shotType": "BACKHAND",
      "total": 193,
      "winnerRate": 0.3005181347150259,
      "adjustedEffectiveness": -0.09170801369486808
    },
    {
      "shotType": "BACKHAND_SLICE",
      "total": 67,
      "winnerRate": 0.31343283582089554,
      "adjustedEffectiveness": -0.07879331258899847
    },
    {
      "shotType": "FOREHAND",
      "total": 243,
      "winnerRate": 0.39094650205761317,
      "adjustedEffectiveness": -0.0012796463522808388
    },
    {
      "shotType": "SERVE",
      "total": 207,
      "winnerRate": 0.4927536231884058,
      "adjustedEffectiveness": 0.10052747477851182
    }
  ],
  "losses": [
    {
      "shotType": "BACKHAND",
      "total": 55,
      "winnerRate": 0.45454545454545453,
      "adjustedEffectiveness": 0.062319306135560526
    },
    {
      "shotType": "BACKHAND_SLICE",
      "total": 46,
      "winnerRate": 0.34782608695652173,
      "adjustedEffectiveness": -0.044400061453372275
    },
    {
      "shotType": "FOREHAND",
      "total": 69,
      "winnerRate": 0.4057971014492754,
      "adjustedEffectiveness": 0.013570953039381384
    },
    {
      "shotType": "SERVE",
      "total": 76,
      "winnerRate": 0.47368421052631576,
      "adjustedEffectiveness": 0.08145806211642176
    }
  ]
}