{"wins":[],"losses":[{"shotType":"FOREHAND","total":94,"winners":11,"errors":15,"effectiveness":-0.043,"winnerRate":0.117,"errorRate":0.16,"winnerCI":{"lower":0.066613,"upper":0.197504,"center":0.132058},"errorCI":{"lower":0.099155,"upper":0.246726,"center":0.172941},"confidence":"high"},{"shotType":"SERVE","total":94,"winners":0,"errors":0,"effectiveness":0,"winnerRate":0,"errorRate":0,"winnerCI":{"lower":0,"upper":0.039263,"center":0.019632},"errorCI":{"lower":0,"upper":0.039263,"center":0.019632},"confidence":"high"},{"shotType":"BACKHAND","total":74,"winners":1,"errors":6,"effectiveness":-0.068,"winnerRate":0.014,"errorRate":0.081,"winnerCI":{"lower":0.002389,"upper":0.072655,"center":0.037522},"errorCI":{"lower":0.037689,"upper":0.165821,"center":0.101755},"confidence":"high"},{"shotType":"BACKHAND_SLICE","total":29,"winners":0,"errors":10,"effectiveness":-0.345,"winnerRate":0,"errorRate":0.345,"winnerCI":{"lower":0,"upper":0.116974,"center":0.058487},"errorCI":{"lower":0.199405,"upper":0.526552,"center":0.362979},"confidence":"low"},{"shotType":"FOREHAND_SLICE","total":9,"winners":0,"errors":3,"effectiveness":-0.333,"winnerRate":0,"errorRate":0.333,"winnerCI":{"lower":0,"upper":0.299153,"center":0.149576},"errorCI":{"lower":0.120582,"upper":0.645803,"center":0.383192},"confidence":"insufficient"},{"shotType":"FOREHAND_VOLLEY","total":2,"winners":1,"errors":0,"effectiveness":0.5,"winnerRate":0.5,"errorRate":0,"winnerCI":{"lower":0.094529,"upper":0.905471,"center":0.5},"errorCI":{"lower":0,"upper":0.657628,"center":0.328814},"confidence":"insufficient"},{"shotType":"FOREHAND_DROP","total":2,"winners":1,"errors":0,"effectiveness":0.5,"winnerRate":0.5,"errorRate":0,"winnerCI":{"lower":0.094529,"upper":0.905471,"center":0.5},"errorCI":{"lower":0,"upper":0.657628,"center":0.328814},"confidence":"insufficient"},{"shotType":"BACKHAND_DROP","total":2,"winners":1,"errors":0,"effectiveness":0.5,"winnerRate":0.5,"errorRate":0,"winnerCI":{"lower":0.094529,"upper":0.905471,"center":0.5},"errorCI":{"lower":0,"upper":0.657628,"center":0.328814},"confidence":"insufficient"},{"shotType":"FOREHAND_LOB","total":2,"winners":0,"errors":1,"effectiveness":-0.5,"winnerRate":0,"errorRate":0.5,"winnerCI":{"lower":0,"upper":0.657628,"center":0.328814},"errorCI":{"lower":0.094529,"upper":0.905471,"center":0.5},"confidence":"insufficient"},{"shotType":"FOREHAND_SWINGING_VOLLEY","total":2,"winners":1,"errors":0,"effectiveness":0.5,"winnerRate":0.5,"errorRate":0,"winnerCI":{"lower":0.094529,"upper":0.905471,"center":0.5},"errorCI":{"lower":0,"upper":0.657628,"center":0.328814},"confidence":"insufficient"},{"shotType":"BACKHAND_VOLLEY","total":1,"winners":0,"errors":0,"effectiveness":0,"winnerRate":0,"errorRate":0,"winnerCI":{"lower":0,"upper":0.793457,"center":0.396728},"errorCI":{"lower":0,"upper":0.793457,"center":0.396728},"confidence":"insufficient"},{"shotType":"BACKHAND_SMASH","total":1,"winners":0,"errors":1,"effectiveness":-1,"winnerRate":0,"errorRate":1,"winnerCI":{"lower":0,"upper":0.793457,"center":0.396728},"errorCI":{"lower":0.206543,"upper":1,"center":0.603272},"confidence":"insufficient"},{"shotType":"TRICK","total":1,"winners":0,"errors":1,"effectiveness":-1,"winnerRate":0,"errorRate":1,"winnerCI":{"lower":0,"upper":0.793457,"center":0.396728},"errorCI":{"lower":0.206543,"upper":1,"center":0.603272},"confidence":"insufficient"}]}